stacs/native/archive.cpython-39-i386-linux-gnu.so
stacs/native/archive/src/archivereader.cpp
stacs/native/archive/src/archivereader.hpp
stacs/native/archive/src/archiveentry.hpp
stacs/native/archive/src/archive.cpp
stacs/native/archive/src/archiveentry.cpp
stacs/scan/exceptions.py
stacs/scan/__init__.py
stacs/scan/__about__.py
stacs/scan/constants.py
stacs/scan/helper.py
stacs/scan/loader/archive.py
stacs/scan/loader/__init__.py
stacs/scan/loader/manifest.py
stacs/scan/loader/filepath.py
stacs/scan/loader/format/__init__.py
stacs/scan/loader/format/xar.py
stacs/scan/loader/format/dmg.py
stacs/scan/scanner/rules.py
stacs/scan/scanner/__init__.py
stacs/scan/entrypoint/__init__.py
stacs/scan/entrypoint/cli.py
stacs/scan/model/pack.py
stacs/scan/model/__init__.py
stacs/scan/model/manifest.py
stacs/scan/model/finding.py
stacs/scan/model/ignore_list.py
stacs/scan/output/__init__.py
stacs/scan/output/pretty.py
stacs/scan/output/markdown.py
stacs/scan/output/sarif.py
stacs/scan/filter/__init__.py
stacs/scan/filter/ignore_list.py
stacs-0.5.1.dist-info/RECORD
stacs-0.5.1.dist-info/METADATA
stacs-0.5.1.dist-info/LICENSE
stacs-0.5.1.dist-info/top_level.txt
stacs-0.5.1.dist-info/WHEEL
stacs-0.5.1.dist-info/entry_points.txt
stacs.libs/libarchive-893cb320.so.13.6.1
