Metadata-Version: 2.1
Name: stacs
Version: 0.5.1
Summary: Static Token And Credential Scanner.
Author: Peter Adkins
License: BSD-3-Clause
Classifier: Programming Language :: Python :: 3.8
Classifier: Natural Language :: English
Requires-Python: >=3.8
License-File: LICENSE
Requires-Dist: click (<9.0,>=8.1.0)
Requires-Dist: yara-python (==4.2.3)
Requires-Dist: pydantic (<2.0,>=1.10.0)
Requires-Dist: colorama (<1.0,>=0.4.0)
Requires-Dist: zstandard (<1.0,>=0.18.0)
Provides-Extra: tests
Requires-Dist: black ; extra == 'tests'
Requires-Dist: coverage ; extra == 'tests'
Requires-Dist: ruff ; extra == 'tests'
Requires-Dist: types-setuptools ; extra == 'tests'
Requires-Dist: mypy ; extra == 'tests'
Requires-Dist: pip-tools ; extra == 'tests'
Requires-Dist: mock ; extra == 'tests'
Requires-Dist: pytest ; extra == 'tests'
Requires-Dist: pytest-cov ; extra == 'tests'
Requires-Dist: responses ; extra == 'tests'
Requires-Dist: tox ; extra == 'tests'
Requires-Dist: ipython ; extra == 'tests'
